{
    "images": [
        {
            "filename": "images/science_journals/4.png",
            "category": "science_journals",
            "description": "a boat with a crab in it"
        },
        {
            "filename": "images/science_journals/4.png",
            "category": "travel",
            "description": "a boat with a crab in it"
        },
        {
            "filename": "images/science_journals/4.png",
            "category": "news",
            "description": "a boat with a crab in it"
        },
        {
            "filename": "images/shopping/6.png",
            "category": "shopping",
            "description": "a snowboarder standing on a snow covered hill"
        },
        {
            "filename": "images/shopping/6.png",
            "category": "travel",
            "description": "a snowboarder standing on a snow covered hill"
        },
        {
            "filename": "images/shopping/6.png",
            "category": "social_media",
            "description": "a snowboarder standing on a snow covered hill"
        },
        {
            "filename": "images/science_journals/2.png",
            "category": "science_journals",
            "description": "a man and woman in wetsuits"
        },
        {
            "filename": "images/science_journals/2.png",
            "category": "travel",
            "description": "a man and woman in wetsuits"
        },
        {
            "filename": "images/science_journals/2.png",
            "category": "social_media",
            "description": "a man and woman in wetsuits"
        },
        {
            "filename": "images/science_journals/2.png",
            "category": "health",
            "description": "a man and woman in wetsuits"
        },
        {
            "filename": "images/health/2.png",
            "category": "health",
            "description": "a woman running on a mountain"
        },
        {
            "filename": "images/health/2.png",
            "category": "travel",
            "description": "a woman running on a mountain"
        },
        {
            "filename": "images/health/2.png",
            "category": "science_journals",
            "description": "a woman running on a mountain"
        },
        {
            "filename": "images/travel/4.png",
            "category": "travel",
            "description": "a skier on a mountain"
        },
        {
            "filename": "images/travel/4.png",
            "category": "social_media",
            "description": "a skier on a mountain"
        },
        {
            "filename": "images/travel/4.png",
            "category": "health",
            "description": "a skier on a mountain"
        },
        {
            "filename": "images/travel/5.png",
            "category": "travel",
            "description": "a woman walking down a street with her suitcase"
        },
        {
            "filename": "images/travel/5.png",
            "category": "shopping",
            "description": "a woman walking down a street with her suitcase"
        },
        {
            "filename": "images/travel/5.png",
            "category": "social_media",
            "description": "a woman walking down a street with her suitcase"
        },
        {
            "filename": "images/social_media/1.png",
            "category": "social_media",
            "description": "a man with dreadlocks wearing a jacket and pants"
        },
        {
            "filename": "images/social_media/1.png",
            "category": "shopping",
            "description": "a man with dreadlocks wearing a jacket and pants"
        },
        {
            "filename": "images/shopping/4.png",
            "category": "shopping",
            "description": "the pool at the holiday inn in san diego"
        },
        {
            "filename": "images/shopping/4.png",
            "category": "travel",
            "description": "the pool at the holiday inn in san diego"
        },
        {
            "filename": "images/shopping/4.png",
            "category": "social_media",
            "description": "the pool at the holiday inn in san diego"
        },
        {
            "filename": "images/science_journals/5.png",
            "category": "science_journals",
            "description": "people fishing in the river"
        },
        {
            "filename": "images/science_journals/5.png",
            "category": "travel",
            "description": "people fishing in the river"
        },
        {
            "filename": "images/health/3.png",
            "category": "health",
            "description": "a woman in a pink sports bra top"
        },
        {
            "filename": "images/health/3.png",
            "category": "shopping",
            "description": "a woman in a pink sports bra top"
        },
        {
            "filename": "images/shopping/7.png",
            "category": "shopping",
            "description": "a man wearing a white t - shirt"
        },
        {
            "filename": "images/shopping/7.png",
            "category": "social_media",
            "description": "a man wearing a white t - shirt"
        },
        {
            "filename": "images/news_journals/15.png",
            "category": "news",
            "description": "a woman performing an indian dance"
        },
        {
            "filename": "images/news_journals/15.png",
            "category": "shopping",
            "description": "a woman performing an indian dance"
        },
        {
            "filename": "images/news_journals/15.png",
            "category": "travel",
            "description": "a woman performing an indian dance"
        },
        {
            "filename": "images/travel/6.png",
            "category": "travel",
            "description": "a bowl of noodles with vegetables"
        },
        {
            "filename": "images/travel/6.png",
            "category": "social_media",
            "description": "a bowl of noodles with vegetables"
        },
        {
            "filename": "images/travel/6.png",
            "category": "health",
            "description": "a bowl of noodles with vegetables"
        },
        {
            "filename": "images/social_media/7.png",
            "category": "social_media",
            "description": "a man in a black shirt standing in front of"
        },
        {
            "filename": "images/social_media/7.png",
            "category": "science_journals",
            "description": "a man in a black shirt standing in front of"
        },
        {
            "filename": "images/social_media/7.png",
            "category": "news",
            "description": "a man in a black shirt standing in front of"
        },
        {
            "filename": "images/travel/2.png",
            "category": "travel",
            "description": "a scuba diver in the ocean"
        },
        {
            "filename": "images/travel/2.png",
            "category": "science_journals",
            "description": "a scuba diver in the ocean"
        },
        {
            "filename": "images/shopping/3.png",
            "category": "shopping",
            "description": "a man with a beard sitting on a rock near"
        },
        {
            "filename": "images/shopping/3.png",
            "category": "social_media",
            "description": "a man with a beard sitting on a rock near"
        },
        {
            "filename": "images/social_media/5.png",
            "category": "social_media",
            "description": "the women's soccer team"
        },
        {
            "filename": "images/social_media/5.png",
            "category": "news",
            "description": "the women's soccer team"
        },
        {
            "filename": "images/travel/7.png",
            "category": "news",
            "description": "a woman taking a picture of a narrow alley"
        },
        {
            "filename": "images/news_journals/4.png",
            "category": "news",
            "description": "a seal on the beach"
        },
        {
            "filename": "images/news_journals/4.png",
            "category": "science_journals",
            "description": "a seal on the beach"
        },
        {
            "filename": "images/news_journals/8.png",
            "category": "news",
            "description": "a man giving a speech"
        },
        {
            "filename": "images/science_journals/1.png",
            "category": "science_journals",
            "description": "a building that has been destroyed"
        },
        {
            "filename": "images/science_journals/1.png",
            "category": "news",
            "description": "a building that has been destroyed"
        },
        {
            "filename": "images/science_journals/1.png",
            "category": "health",
            "description": "a building that has been destroyed"
        },
        {
            "filename": "images/health/5.png",
            "category": "health",
            "description": "a woman kiteboarding in the ocean"
        },
        {
            "filename": "images/news_journals/25.png",
            "category": "news"
        },
        {
            "filename": "images/news_journals/11.png",
            "category": "news"
        },
        {
            "filename": "images/shopping/1.png",
            "category": "shopping"
        },
        {
            "filename": "images/news_journals/35.png",
            "category": "news"
        },
        {
            "filename": "images/health/4.png",
            "category": "health"
        },
        {
            "filename": "images/health/7.png",
            "category": "health"
        },
        {
            "filename": "images/health/1.png",
            "category": "health"
        },
        {
            "filename": "images/health/6.png",
            "category": "health"
        },
        {
            "filename": "images/shopping/2.png",
            "category": "shopping"
        },
        {
            "filename": "images/science_journals/3.png",
            "category": "science_journals"
        },
        {
            "filename": "images/shopping/5.png",
            "category": "shopping"
        },
        {
            "filename": "images/science_journals/6.png",
            "category": "science_journals"
        },
        {
            "filename": "images/science_journals/7.png",
            "category": "science_journals"
        }
    ]
}